veeti/__init__.py
veeti/main.py
veeti-0.1.2.dist-info/METADATA
veeti-0.1.2.dist-info/WHEEL
veeti-0.1.2.dist-info/RECORD
