Metadata-Version: 2.3
Name: veeti
Version: 0.1.2
Summary: 
Author: poksiala
Author-email: panu@oksiala.fi
Requires-Python: >=3.11,<4.0.0
Classifier: Programming Language :: Python :: 3
Classifier: Programming Language :: Python :: 3.11
Classifier: Programming Language :: Python :: 3.12
Classifier: Programming Language :: Python :: 3.13
Requires-Dist: fastapi[standard] (>=0.115.12,<0.116.0)
Requires-Dist: loguru (>=0.7.3,<0.8.0)
Requires-Dist: requests (>=2.32.3,<3.0.0)
